cxt_mcp_plus/__init__.py
cxt_mcp_plus-0.1.0.dist-info/WHEEL
cxt_mcp_plus-0.1.0.dist-info/entry_points.txt
cxt_mcp_plus-0.1.0.dist-info/METADATA
cxt_mcp_plus-0.1.0.dist-info/RECORD
